[
    {
        "id": "post-5786229475",
        "parentId": "post-5786229475",
        "message": "So they didn't even return to their own world but in this new world the red moon exists, which means liselotte is alive in this world, so basically they just delayed the inevitable and nothing really changed after all that struggle.",
        "authorName": "Cosmic Defender",
        "authorId": "akshayvnair",
        "authorAvatar": "https://c.disquscdn.com/uploads/users/29270/1687/avatar92.jpg?1639425976",
        "timeCreation": "Saturday, March 12, 2022 1:55 AM"
    },
    {
        "id": "post-5826635083",
        "parentId": "post-5826635083",
        "message": "well they did seal her away again and if no one has memories of the crimson night then they cant use the powers of the stone fragments which means in the new world the only one who has memory from the previous worlds in the aeons eye holder because he can see through time and space with his power",
        "authorName": "loudguy",
        "authorId": "loudguy",
        "authorAvatar": "https://c.disquscdn.com/uploads/users/37130/9087/avatar92.jpg?1625122785",
        "timeCreation": "Thursday, April 14, 2022 4:57 AM"
    }
]