[
    {
        "id": "post-5750368967",
        "parentId": "post-5750368967",
        "message": "Sakyo aged back 20 years😭",
        "authorName": "Princess Compuesto",
        "authorId": "princesscompuesto",
        "authorAvatar": "https://a.disquscdn.com/1658911552/images/noavatar92.png",
        "timeCreation": "Sunday, February 20, 2022 10:34 AM"
    },
    {
        "id": "post-5750368134",
        "parentId": "post-5750368134",
        "message": "HYODO WAS SOOOO GOOD!!!",
        "authorName": "Princess Compuesto",
        "authorId": "princesscompuesto",
        "authorAvatar": "https://a.disquscdn.com/1658911552/images/noavatar92.png",
        "timeCreation": "Sunday, February 20, 2022 10:34 AM"
    },
    {
        "id": "post-5750365324",
        "parentId": "post-5750365324",
        "message": "I wanna know the whole story of Nanao and his \"Yuki\" and also Ban-chan's actual portrait!!!",
        "authorName": "Princess Compuesto",
        "authorId": "princesscompuesto",
        "authorAvatar": "https://a.disquscdn.com/1658911552/images/noavatar92.png",
        "timeCreation": "Sunday, February 20, 2022 10:33 AM"
    },
    {
        "id": "post-5750361106",
        "parentId": "post-5750361106",
        "message": "Hurah for an actual lead!",
        "authorName": "Princess Compuesto",
        "authorId": "princesscompuesto",
        "authorAvatar": "https://a.disquscdn.com/1658911552/images/noavatar92.png",
        "timeCreation": "Sunday, February 20, 2022 10:32 AM"
    }
]