[
    {
        "id": "post-5912907124",
        "parentId": "post-5912907124",
        "message": "This 3 min intro is too much!!!",
        "authorName": "lo_zero",
        "authorId": "lo_zero",
        "authorAvatar": "https://a.disquscdn.com/1658911552/images/noavatar92.png",
        "timeCreation": "Monday, July 11, 2022 1:07 AM"
    },
    {
        "id": "post-5912122393",
        "parentId": "post-5912122393",
        "message": "Just add another body to the list",
        "authorName": "Gr8H",
        "authorId": "disqus_Gr8Huligan",
        "authorAvatar": "https://a.disquscdn.com/1658911552/images/noavatar92.png",
        "timeCreation": "Sunday, July 10, 2022 2:01 AM"
    },
    {
        "id": "post-5911251433",
        "parentId": "post-5911251433",
        "message": "",
        "authorName": "Vincent",
        "authorId": "VincentiousFormulae",
        "authorAvatar": "https://a.disquscdn.com/1658911552/images/noavatar92.png",
        "timeCreation": "Saturday, July 9, 2022 1:51 AM"
    },
    {
        "id": "post-5910772641",
        "parentId": "post-5910772641",
        "message": "Tan Yun's going to have to show Senior Sun who's the better man.",
        "authorName": "VCH",
        "authorId": "disqus_ma4zxnbTyd",
        "authorAvatar": "https://a.disquscdn.com/1658911552/images/noavatar92.png",
        "timeCreation": "Friday, July 8, 2022 4:51 PM"
    },
    {
        "id": "post-5910744989",
        "parentId": "post-5910744989",
        "message": ":)",
        "authorName": "Festivex🎄🔞",
        "authorId": "disqus_S8kIwC9Htk",
        "authorAvatar": "https://a.disquscdn.com/1658911552/images/noavatar92.png",
        "timeCreation": "Friday, July 8, 2022 4:00 PM"
    },
    {
        "id": "post-5910730582",
        "parentId": "post-5910730582",
        "message": "Me here",
        "authorName": "DEMON LORD ™",
        "authorId": "Demon____Lord",
        "authorAvatar": "https://a.disquscdn.com/1658911552/images/noavatar92.png",
        "timeCreation": "Friday, July 8, 2022 3:32 PM"
    }
]