[
    {
        "id": "post-5903814356",
        "parentId": "post-5903814356",
        "message": "I hope nothing happens to her",
        "authorName": "rinharu",
        "authorId": "nelesehm",
        "authorAvatar": "https://a.disquscdn.com/1658911552/images/noavatar92.png",
        "timeCreation": "Friday, July 1, 2022 6:11 AM"
    },
    {
        "id": "post-5684816930",
        "parentId": "post-5684816930",
        "message": "I will say this honestly I didn’t cry for almost about 3 years on an anime movie even the spider man no way home and I cried at this ending of this eps I don’t but it broke my heart",
        "authorName": "The idiot online",
        "authorId": "theidiotonline",
        "authorAvatar": "https://a.disquscdn.com/1658911552/images/noavatar92.png",
        "timeCreation": "Monday, January 10, 2022 11:25 PM"
    },
    {
        "id": "post-5673975424",
        "parentId": "post-5673975424",
        "message": "Yuka-san!!1!1!1 :v :(",
        "authorName": "SIMP",
        "authorId": "Wellthats_nice",
        "authorAvatar": "https://a.disquscdn.com/1658911552/images/noavatar92.png",
        "timeCreation": "Tuesday, January 4, 2022 9:20 PM"
    },
    {
        "id": "post-5669581914",
        "parentId": "post-5669581914",
        "message": "no, not the birds... rly bro.. D:",
        "authorName": "Kenma",
        "authorId": "jonzukun",
        "authorAvatar": "https://a.disquscdn.com/1658911552/images/noavatar92.png",
        "timeCreation": "Sunday, January 2, 2022 5:39 AM"
    },
    {
        "id": "post-5629812550",
        "parentId": "post-5629812550",
        "message": "Idk why but at 16:00 of the ep i started listening to Legends by Juice WRLD T_T",
        "authorName": "Kenpachi.Zaraki",
        "authorId": "disqus_GUND2EObnA",
        "authorAvatar": "https://a.disquscdn.com/1658911552/images/noavatar92.png",
        "timeCreation": "Thursday, December 2, 2021 1:56 PM"
    },
    {
        "id": "post-5604931998",
        "parentId": "post-5604931998",
        "message": "dang there is something in my eye",
        "authorName": "Sad bro",
        "authorId": "disqus_SIqORaVdvu",
        "authorAvatar": "https://a.disquscdn.com/1658911552/images/noavatar92.png",
        "timeCreation": "Thursday, November 11, 2021 11:16 PM"
    },
    {
        "id": "post-5585283965",
        "parentId": "post-5585283965",
        "message": "Man, they gotta put onion in this episode, when we havent even known the result",
        "authorName": "Shigeno",
        "authorId": "SHIGEN0",
        "authorAvatar": "https://a.disquscdn.com/1658911552/images/noavatar92.png",
        "timeCreation": "Tuesday, October 26, 2021 10:21 PM"
    },
    {
        "id": "post-5468837065",
        "parentId": "post-5468837065",
        "message": "Bored, can’t really relate anymore, the anime keeps changing the pace, slow fast slow fast, the tides changing from mc team to enemy team over and over again, nothing new or exciting to keep me entertained",
        "authorName": "RFLB",
        "authorId": "RFLBgaming",
        "authorAvatar": "https://a.disquscdn.com/1658911552/images/noavatar92.png",
        "timeCreation": "Sunday, July 25, 2021 7:47 PM"
    },
    {
        "id": "post-5485417298",
        "parentId": "post-5485417298",
        "message": "That's all sport anime can offer , if you don't like why are you watchin' .",
        "authorName": "Tracer",
        "authorId": "disqus_cGvwYAOUGi",
        "authorAvatar": "https://a.disquscdn.com/1658911552/images/noavatar92.png",
        "timeCreation": "Saturday, August 7, 2021 8:18 PM"
    }
]