[
    {
        "id": "post-5914311367",
        "parentId": "post-5914311367",
        "message": "Wtf is this? I was really into the romance between the mc and the first girl, cmon.",
        "authorName": "Harem_King",
        "authorId": "disqus_I0729L3izt",
        "authorAvatar": "https://a.disquscdn.com/1658911552/images/noavatar92.png",
        "timeCreation": "Tuesday, July 12, 2022 1:33 PM"
    },
    {
        "id": "post-5902910306",
        "parentId": "post-5902910306",
        "message": "i wish their was only one girl nd that would be kaoru",
        "authorName": "Tejas",
        "authorId": "disqus_8PC70vDJIz",
        "authorAvatar": "https://a.disquscdn.com/1658911552/images/noavatar92.png",
        "timeCreation": "Thursday, June 30, 2022 11:10 AM"
    },
    {
        "id": "post-5902351020",
        "parentId": "post-5902351020",
        "message": "This is it, i am done with this anime. Time for Next anime",
        "authorName": "Ruinor",
        "authorId": "ruinor",
        "authorAvatar": "https://a.disquscdn.com/1658911552/images/noavatar92.png",
        "timeCreation": "Wednesday, June 29, 2022 10:34 PM"
    },
    {
        "id": "post-5899662096",
        "parentId": "post-5899662096",
        "message": "for those who are confused this is one of those anime's with different routes if you want you can search on google for what episode your favorite girl route is and it also includes for s2 and the ova's",
        "authorName": "Tyshaun",
        "authorId": "disqus_toaPI4naeb",
        "authorAvatar": "https://a.disquscdn.com/1658911552/images/noavatar92.png",
        "timeCreation": "Monday, June 27, 2022 8:27 AM"
    },
    {
        "id": "post-5890089717",
        "parentId": "post-5890089717",
        "message": "Okay, so my honest opinion (even though it's only episode 5):",
        "authorName": "Naxu",
        "authorId": "AnimuNaxu",
        "authorAvatar": "https://c.disquscdn.com/uploads/users/34640/7348/avatar92.jpg?1616246672",
        "timeCreation": "Friday, June 17, 2022 4:36 AM"
    },
    {
        "id": "post-5839176734",
        "parentId": "post-5839176734",
        "message": "so, this is a siren type of story. Parallel timeline, where Haruka and MC wont be anything",
        "authorName": "A 909✔️ᵛᵉʳᶦᶠᶦᵉᵈ",
        "authorId": "a_909",
        "authorAvatar": "https://c.disquscdn.com/uploads/users/36537/3606/avatar92.jpg?1642696662",
        "timeCreation": "Tuesday, April 26, 2022 5:02 PM"
    },
    {
        "id": "post-5876016771",
        "parentId": "post-5876016771",
        "message": "Yep and since I've that I'm gone",
        "authorName": "rated-r84gg",
        "authorId": "ratedr84gg",
        "authorAvatar": "https://c.disquscdn.com/uploads/users/37152/3265/avatar92.jpg?1624769894",
        "timeCreation": "Friday, June 3, 2022 6:59 AM"
    },
    {
        "id": "post-5830808138",
        "parentId": "post-5830808138",
        "message": "Mah head is paining.....",
        "authorName": "Samrat Roy",
        "authorId": "disqus_TyZ4w1Vdn3",
        "authorAvatar": "https://a.disquscdn.com/1658911552/images/noavatar92.png",
        "timeCreation": "Monday, April 18, 2022 10:51 AM"
    },
    {
        "id": "post-5797820335",
        "parentId": "post-5797820335",
        "message": "Its like a different multi verse",
        "authorName": "प्रेम घ्याप्रुङ गुरुङ्ग",
        "authorId": "disqus_aL5HhS3Cg8",
        "authorAvatar": "https://a.disquscdn.com/1658911552/images/noavatar92.png",
        "timeCreation": "Sunday, March 20, 2022 10:18 PM"
    },
    {
        "id": "post-5790601950",
        "parentId": "post-5790601950",
        "message": "Honestly Kaoru is my favorite out of all of them. Their relationship just seems far more natural, especially transitioning from childhood friend to dating.She's funny, and they seem really comfortable around each other. Their chemistry is really good too, better than the senpai chick.",
        "authorName": "retard",
        "authorId": "disqus_SJ72lUapD7",
        "authorAvatar": "https://a.disquscdn.com/1658911552/images/noavatar92.png",
        "timeCreation": "Tuesday, March 15, 2022 10:39 PM"
    },
    {
        "id": "post-5772441157",
        "parentId": "post-5772441157",
        "message": "9:37, Junichi you came lol, really you cheated on Haruka and came in your friend. im just kidding though, i know it's a different timeline but i just had to throw that in there.",
        "authorName": "Junichi Ramirez",
        "authorId": "blueraven89",
        "authorAvatar": "https://a.disquscdn.com/1658911552/images/noavatar92.png",
        "timeCreation": "Monday, February 28, 2022 2:32 PM"
    },
    {
        "id": "post-5720477849",
        "parentId": "post-5720477849",
        "message": "aww",
        "authorName": "Twick",
        "authorId": "disqus_iUsvmNJ24W",
        "authorAvatar": "https://a.disquscdn.com/1658911552/images/noavatar92.png",
        "timeCreation": "Friday, February 4, 2022 2:15 AM"
    },
    {
        "id": "post-5707408051",
        "parentId": "post-5707408051",
        "message": "i ship kaoru to him yeh",
        "authorName": "Aesta",
        "authorId": "disqus_lJbPyjjTG0",
        "authorAvatar": "https://a.disquscdn.com/1658911552/images/noavatar92.png",
        "timeCreation": "Tuesday, January 25, 2022 10:24 PM"
    },
    {
        "id": "post-5698150398",
        "parentId": "post-5698150398",
        "message": "Kaoru is my favorite girl!",
        "authorName": "Chiro",
        "authorId": "disqus_QjDiOYv6bF",
        "authorAvatar": "https://a.disquscdn.com/1658911552/images/noavatar92.png",
        "timeCreation": "Wednesday, January 19, 2022 2:35 PM"
    },
    {
        "id": "post-5674257033",
        "parentId": "post-5674257033",
        "message": "This is some next level multiverse shit😂",
        "authorName": "OBANOS",
        "authorId": "himanshb",
        "authorAvatar": "https://a.disquscdn.com/1658911552/images/noavatar92.png",
        "timeCreation": "Wednesday, January 5, 2022 12:21 AM"
    },
    {
        "id": "post-5601811642",
        "parentId": "post-5601811642",
        "message": "my theory was correcto",
        "authorName": "Boywonder247",
        "authorId": "boywonder247",
        "authorAvatar": "https://a.disquscdn.com/1658911552/images/noavatar92.png",
        "timeCreation": "Tuesday, November 9, 2021 8:37 AM"
    },
    {
        "id": "post-5563365675",
        "parentId": "post-5563365675",
        "message": "For some reason is this anime the same as that one particular anime that I totally forgot the anime name but that anime has only 13 ep and 3 girls with different future if he chooses from one of them but this it's like the copyright version but there's 26 ep total and there's more than 3 girls with different future",
        "authorName": "KiNG",
        "authorId": "mdizzanshahiransamsuddin",
        "authorAvatar": "https://a.disquscdn.com/1658911552/images/noavatar92.png",
        "timeCreation": "Friday, October 8, 2021 11:17 AM"
    },
    {
        "id": "post-5597356001",
        "parentId": "post-5597356001",
        "message": "Funny thing you mention that, this anime is actually the prequel to Seiren. Their universe and timeline are connected. In seiren you can see some amagami characters cameo in seiren (for example, ikuo who is the mc’s best friend is actually ai nanasaki’s little brother)",
        "authorName": "The Chosen One",
        "authorId": "disqus_wZLLKY9Hm7",
        "authorAvatar": "https://a.disquscdn.com/1658911552/images/noavatar92.png",
        "timeCreation": "Friday, November 5, 2021 12:10 PM"
    },
    {
        "id": "post-5772451468",
        "parentId": "post-5772451468",
        "message": "only one person is connected and that's Nanasaki, but he's a side character to MC in Seiren.\nRihoko's friends show up in the final arc, but they graduated before her and Rihoko went on to something else.",
        "authorName": "Junichi Ramirez",
        "authorId": "blueraven89",
        "authorAvatar": "https://a.disquscdn.com/1658911552/images/noavatar92.png",
        "timeCreation": "Monday, February 28, 2022 2:51 PM"
    },
    {
        "id": "post-5589229835",
        "parentId": "post-5589229835",
        "message": "I think ur talking about seiren.....i actually dont like this type of concept....but still watch it",
        "authorName": "Not_sasugay",
        "authorId": "sheikhrounak",
        "authorAvatar": "https://a.disquscdn.com/1658911552/images/noavatar92.png",
        "timeCreation": "Friday, October 29, 2021 10:50 PM"
    },
    {
        "id": "post-5558360745",
        "parentId": "post-5558360745",
        "message": ".... I don't like this idea. I feal like this just drains the whole romantic feal from it.",
        "authorName": "Xavier",
        "authorId": "disqus_hNy4FgxZM9",
        "authorAvatar": "https://a.disquscdn.com/1658911552/images/noavatar92.png",
        "timeCreation": "Monday, October 4, 2021 6:14 PM"
    },
    {
        "id": "post-5705740641",
        "parentId": "post-5705740641",
        "message": "Nah , it makes everyone happy, we get good backstory of all characters, rather than typical childhoods friend tropes",
        "authorName": "ChadKazuma",
        "authorId": "ChadKazuma",
        "authorAvatar": "https://a.disquscdn.com/1658911552/images/noavatar92.png",
        "timeCreation": "Monday, January 24, 2022 7:14 PM"
    },
    {
        "id": "post-5520172724",
        "parentId": "post-5520172724",
        "message": "i like ya cut g",
        "authorName": "xaitor",
        "authorId": "disqus_YWwsNWWOwd",
        "authorAvatar": "https://a.disquscdn.com/1658911552/images/noavatar92.png",
        "timeCreation": "Friday, September 3, 2021 11:15 AM"
    },
    {
        "id": "post-5490413887",
        "parentId": "post-5490413887",
        "message": "i like kaoru more than morishima senpai.. im particularly excited to see this arc",
        "authorName": "Bav",
        "authorId": "BhavyanDaiya",
        "authorAvatar": "https://a.disquscdn.com/1658911552/images/noavatar92.png",
        "timeCreation": "Wednesday, August 11, 2021 10:42 PM"
    },
    {
        "id": "post-5394808921",
        "parentId": "post-5394808921",
        "message": "AYOOO my boy you is a poivert",
        "authorName": "Realwrecke !",
        "authorId": "Kingwrecke",
        "authorAvatar": "https://a.disquscdn.com/1658911552/images/noavatar92.png",
        "timeCreation": "Monday, May 24, 2021 2:53 PM"
    },
    {
        "id": "post-5331118105",
        "parentId": "post-5331118105",
        "message": "ayooo them panties looking nice",
        "authorName": "wronganime_",
        "authorId": "wronganime",
        "authorAvatar": "https://a.disquscdn.com/1658911552/images/noavatar92.png",
        "timeCreation": "Monday, April 5, 2021 10:19 PM"
    },
    {
        "id": "post-5544152585",
        "parentId": "post-5544152585",
        "message": "tf",
        "authorName": "HeldSquire",
        "authorId": "heldsquire",
        "authorAvatar": "https://a.disquscdn.com/1658911552/images/noavatar92.png",
        "timeCreation": "Wednesday, September 22, 2021 6:37 PM"
    },
    {
        "id": "post-5657773831",
        "parentId": "post-5657773831",
        "message": "he's the real life mc of the live action of this anime",
        "authorName": "Kingstan",
        "authorId": "disqus_3LSwVNjdlv",
        "authorAvatar": "https://a.disquscdn.com/1658911552/images/noavatar92.png",
        "timeCreation": "Saturday, December 25, 2021 3:28 AM"
    }
]