[
    {
        "id": "post-5521632263",
        "parentId": "post-5521632263",
        "message": "wahh we've got punk Ebumi like punk Kuramochi and Arakita. I'm sure he will be partially tamed later on by something or someone. I love the wild guys in the team. They always get tamed by some influence.",
        "authorName": "$TheRichDetectiv£",
        "authorId": "themoneylord",
        "authorAvatar": "https://c.disquscdn.com/uploads/users/36224/6095/avatar92.jpg?1619555911",
        "timeCreation": "Saturday, September 4, 2021 3:48 PM"
    }
]