[
    {
        "id": "post-5924013772",
        "parentId": "post-5924013772",
        "message": "I like how that guy in the ending ( I think the author) with each episodes he changes the shirt and his hair gets longer",
        "authorName": "Shinjian4",
        "authorId": "shinjian4",
        "authorAvatar": "https://c.disquscdn.com/uploads/users/38624/3514/avatar92.jpg?1658373298",
        "timeCreation": "Thursday, July 21, 2022 8:44 AM"
    },
    {
        "id": "post-5911415620",
        "parentId": "post-5911415620",
        "message": "ok.... idk how to feel about this ending",
        "authorName": "ShamWOW",
        "authorId": "disqus_q47cMMPsVv",
        "authorAvatar": "https://c.disquscdn.com/uploads/users/38583/3291/avatar92.jpg?1657393414",
        "timeCreation": "Saturday, July 9, 2022 5:39 AM"
    },
    {
        "id": "post-5899806343",
        "parentId": "post-5899806343",
        "message": "mixed feelings about this one, on one hand there's some interesting themes and on the other the MC is a brooding edgelord middle schooler",
        "authorName": "komorebiごみ",
        "authorId": "komorebitrash",
        "authorAvatar": "https://c.disquscdn.com/uploads/users/38460/255/avatar92.jpg?1653266154",
        "timeCreation": "Monday, June 27, 2022 2:01 PM"
    },
    {
        "id": "post-5885398113",
        "parentId": "post-5885398113",
        "message": "This anime gave me a new take on life and made realize what some people think goes in that \"Quiet kid\" and \"Emo kid\" head. Kinda mad he didn't get with saeki. ps. There's a kdrama that has the same title and genre as this one i don't watch kdarma but some might so check it out ig.",
        "authorName": "Bark:)",
        "authorId": "disqus_J0PbCCdiSn",
        "authorAvatar": "https://c.disquscdn.com/uploads/users/37248/7487/avatar92.jpg?1626584149",
        "timeCreation": "Sunday, June 12, 2022 6:09 AM"
    },
    {
        "id": "post-5831372038",
        "parentId": "post-5831372038",
        "message": "Wondering What I just watched?",
        "authorName": "Bereket Mengesha",
        "authorId": "bereketmengesha",
        "authorAvatar": "https://a.disquscdn.com/1658911552/images/noavatar92.png",
        "timeCreation": "Tuesday, April 19, 2022 12:39 AM"
    },
    {
        "id": "post-5889354067",
        "parentId": "post-5889354067",
        "message": "Bro I fucking don't know literally wasted so much time watching this stupid shit",
        "authorName": "Black Wing",
        "authorId": "disqus_1fQOxB7621",
        "authorAvatar": "https://a.disquscdn.com/1658911552/images/noavatar92.png",
        "timeCreation": "Thursday, June 16, 2022 12:37 PM"
    },
    {
        "id": "post-5901258428",
        "parentId": "post-5901258428",
        "message": "read manga",
        "authorName": "vito kalyan",
        "authorId": "vitokalyan",
        "authorAvatar": "https://c.disquscdn.com/uploads/users/26743/9779/avatar92.jpg?1551278911",
        "timeCreation": "Tuesday, June 28, 2022 10:37 PM"
    },
    {
        "id": "post-5901472298",
        "parentId": "post-5901472298",
        "message": "I did",
        "authorName": "Black Wing",
        "authorId": "disqus_1fQOxB7621",
        "authorAvatar": "https://a.disquscdn.com/1658911552/images/noavatar92.png",
        "timeCreation": "Wednesday, June 29, 2022 2:03 AM"
    },
    {
        "id": "post-5613434871",
        "parentId": "post-5613434871",
        "message": "My fav anime",
        "authorName": "xELIXEx",
        "authorId": "xelixex",
        "authorAvatar": "https://c.disquscdn.com/uploads/users/37768/1075/avatar92.jpg?1637262700",
        "timeCreation": "Friday, November 19, 2021 12:40 AM"
    },
    {
        "id": "post-5889354152",
        "parentId": "post-5889354152",
        "message": "Favorite anime bro your taste is shit",
        "authorName": "Black Wing",
        "authorId": "disqus_1fQOxB7621",
        "authorAvatar": "https://a.disquscdn.com/1658911552/images/noavatar92.png",
        "timeCreation": "Thursday, June 16, 2022 12:37 PM"
    },
    {
        "id": "post-5909123711",
        "parentId": "post-5909123711",
        "message": "LMAO Fr",
        "authorName": "2SoliidTaii ⍥",
        "authorId": "taiveon",
        "authorAvatar": "https://a.disquscdn.com/1658911552/images/noavatar92.png",
        "timeCreation": "Thursday, July 7, 2022 12:16 AM"
    },
    {
        "id": "post-5605773512",
        "parentId": "post-5605773512",
        "message": "and that's how EMO KIDS were born poor troubled souls",
        "authorName": "dizijohnson",
        "authorId": "dizijohnson",
        "authorAvatar": "https://a.disquscdn.com/1658911552/images/noavatar92.png",
        "timeCreation": "Friday, November 12, 2021 5:55 PM"
    },
    {
        "id": "post-5590258723",
        "parentId": "post-5590258723",
        "message": "This anime gave me whole new level of headache & mental pressure. Damn 💀",
        "authorName": "Monkey D San",
        "authorId": "monkeydsan",
        "authorAvatar": "https://a.disquscdn.com/1658911552/images/noavatar92.png",
        "timeCreation": "Saturday, October 30, 2021 8:07 PM"
    },
    {
        "id": "post-5476684346",
        "parentId": "post-5476684346",
        "message": "i need season 2",
        "authorName": "Irboen",
        "authorId": "irboen",
        "authorAvatar": "https://a.disquscdn.com/1658911552/images/noavatar92.png",
        "timeCreation": "Saturday, July 31, 2021 4:43 PM"
    },
    {
        "id": "post-5481907004",
        "parentId": "post-5481907004",
        "message": "I recommend you to read the manga it does all of this but does it in a much better way. Looking at when this was released it doesn't look like it will get a season 2. if you plan to read it, read it from chapter 20.",
        "authorName": "Darren Benn",
        "authorId": "darren_benn",
        "authorAvatar": "https://a.disquscdn.com/1658911552/images/noavatar92.png",
        "timeCreation": "Thursday, August 5, 2021 12:12 AM"
    },
    {
        "id": "post-5881210728",
        "parentId": "post-5881210728",
        "message": "Not in a much better way in hell, surely a normal anime direction couldn't do such elaborate real-like gestures through rotoscopy with jp voice acting, which is known for being better than acting in live action. Idk why there's such a common shit-take, probably sums up anime fans.",
        "authorName": "Ichinosebestboi",
        "authorId": "jackcruiser",
        "authorAvatar": "https://a.disquscdn.com/1658911552/images/noavatar92.png",
        "timeCreation": "Tuesday, June 7, 2022 10:40 PM"
    },
    {
        "id": "post-5881824995",
        "parentId": "post-5881824995",
        "message": "Okay, ichinosebestboi. I apologize that I have a different opinion than yours.",
        "authorName": "Darren Benn",
        "authorId": "darren_benn",
        "authorAvatar": "https://a.disquscdn.com/1658911552/images/noavatar92.png",
        "timeCreation": "Wednesday, June 8, 2022 2:51 PM"
    },
    {
        "id": "post-5613436705",
        "parentId": "post-5613436705",
        "message": "Where?",
        "authorName": "xELIXEx",
        "authorId": "xelixex",
        "authorAvatar": "https://a.disquscdn.com/1658911552/images/noavatar92.png",
        "timeCreation": "Friday, November 19, 2021 12:42 AM"
    },
    {
        "id": "post-5613455217",
        "parentId": "post-5613455217",
        "message": "mangasee123. com",
        "authorName": "Darren Benn",
        "authorId": "darren_benn",
        "authorAvatar": "https://a.disquscdn.com/1658911552/images/noavatar92.png",
        "timeCreation": "Friday, November 19, 2021 12:57 AM"
    }
]