[
    {
        "id": "post-5625869580",
        "parentId": "post-5625869580",
        "message": "Bruh, her sister is like an annoying barking chihuahua…. Shut up already. We get it, you’re defensive and love your onee-chan. Calm down. You just ruined that tender moment of her in his arms.",
        "authorName": "Kingsblade",
        "authorId": "Kingsblade",
        "authorAvatar": "https://a.disquscdn.com/1658911552/images/noavatar92.png",
        "timeCreation": "Monday, November 29, 2021 4:41 PM"
    }
]