[
    {
        "id": "post-5905666802",
        "parentId": "post-5905666802",
        "message": "This was on Roblox :0 (and am first comment :0)",
        "authorName": "Blade",
        "authorId": "disqus_eAEeeeaq2N",
        "authorAvatar": "https://c.disquscdn.com/uploads/users/37347/8768/avatar92.jpg?1643160733",
        "timeCreation": "Sunday, July 3, 2022 8:06 AM"
    },
    {
        "id": "post-5922966250",
        "parentId": "post-5922966250",
        "message": "Nice I was there for the roblox thing",
        "authorName": "King Sparta",
        "authorId": "tyresegarrett",
        "authorAvatar": "https://c.disquscdn.com/uploads/users/36523/995/avatar92.jpg?1643405759",
        "timeCreation": "Wednesday, July 20, 2022 7:38 AM"
    }
]